greeting/__init__.py
greeting/city.py
greeting/constants.py
greeting/template/index.html
my_city_greeting-1.1.2.dist-info/LICENSE
my_city_greeting-1.1.2.dist-info/METADATA
my_city_greeting-1.1.2.dist-info/WHEEL
my_city_greeting-1.1.2.dist-info/top_level.txt
my_city_greeting-1.1.2.dist-info/RECORD
